pynapple/__init__.py
pynapple/core/__init__.py
pynapple/core/_core_functions.py
pynapple/core/_jitted_functions.py
pynapple/core/base_class.py
pynapple/core/config.py
pynapple/core/interval_set.py
pynapple/core/metadata_class.py
pynapple/core/time_index.py
pynapple/core/time_series.py
pynapple/core/ts_group.py
pynapple/core/utils.py
pynapple/io/__init__.py
pynapple/io/cnmfe.py
pynapple/io/folder.py
pynapple/io/interface_npz.py
pynapple/io/interface_nwb.py
pynapple/io/loader.py
pynapple/io/misc.py
pynapple/io/neurosuite.py
pynapple/io/phy.py
pynapple/io/suite2p.py
pynapple/process/__init__.py
pynapple/process/_process_functions.py
pynapple/process/correlograms.py
pynapple/process/decoding.py
pynapple/process/filtering.py
pynapple/process/perievent.py
pynapple/process/randomize.py
pynapple/process/spectrum.py
pynapple/process/tuning_curves.py
pynapple/process/warping.py
pynapple/process/wavelets.py
pynapple-0.10.2.dist-info/licenses/LICENSE
pynapple-0.10.2.dist-info/METADATA
pynapple-0.10.2.dist-info/WHEEL
pynapple-0.10.2.dist-info/top_level.txt
pynapple-0.10.2.dist-info/RECORD
