Metadata-Version: 2.4
Name: pynapple
Version: 0.10.2
Summary: PYthon Neural Analysis Package Pour Laboratoires d’Excellence
Author-email: Guillaume Viejo <guillaume.viejo@gmail.com>
License: MIT License
Project-URL: homepage, http://pynapple.org/
Project-URL: documentation, http://pynapple.org/
Project-URL: repository, https://github.com/pynapple-org/pynapple
Keywords: neuroscience
Classifier: Development Status :: 3 - Alpha
Classifier: Intended Audience :: Science/Research
Classifier: License :: OSI Approved :: MIT License
Classifier: Natural Language :: English
Classifier: Programming Language :: Python :: 3
Classifier: Programming Language :: Python :: 3.8
Classifier: Programming Language :: Python :: 3.9
Classifier: Programming Language :: Python :: 3.10
Requires-Python: >=3.8
License-File: LICENSE
Requires-Dist: pandas>1.0.3
Requires-Dist: numpy>=1.17.4
Requires-Dist: scipy>=1.3.2
Requires-Dist: numba>=0.46.0
Requires-Dist: numba>=0.53.0; python_version >= "3.9"
Requires-Dist: numba>=0.55.0; python_version >= "3.10"
Requires-Dist: numba>=0.57.0; python_version >= "3.11"
Requires-Dist: numba>=0.59.0; python_version >= "3.12"
Requires-Dist: numba>=0.61.0; python_version >= "3.13"
Requires-Dist: pynwb>=2.0.0
Requires-Dist: tabulate
Requires-Dist: h5py
Requires-Dist: rich
Requires-Dist: xarray>=2023.1.0
Provides-Extra: jax
Requires-Dist: pynajax; extra == "jax"
Provides-Extra: dev
Requires-Dist: black>=24.2.0; extra == "dev"
Requires-Dist: isort; extra == "dev"
Requires-Dist: pip-tools; extra == "dev"
Requires-Dist: pytest; extra == "dev"
Requires-Dist: flake8; extra == "dev"
Requires-Dist: Flake8-pyproject; extra == "dev"
Requires-Dist: coverage; extra == "dev"
Provides-Extra: doc
Requires-Dist: matplotlib; extra == "doc"
Requires-Dist: zarr; extra == "doc"
Requires-Dist: seaborn; extra == "doc"
Requires-Dist: tqdm; extra == "doc"
Requires-Dist: numpydoc; extra == "doc"
Requires-Dist: sphinx; extra == "doc"
Requires-Dist: pydata-sphinx-theme; extra == "doc"
Requires-Dist: sphinx-autodoc-typehints; extra == "doc"
Requires-Dist: sphinx-copybutton; extra == "doc"
Requires-Dist: sphinx-design; extra == "doc"
Requires-Dist: sphinx-issues; extra == "doc"
Requires-Dist: sphinxcontrib-apidoc; extra == "doc"
Requires-Dist: myst-parser; extra == "doc"
Requires-Dist: myst-nb; extra == "doc"
Requires-Dist: dandi; extra == "doc"
Requires-Dist: sphinx-autobuild; extra == "doc"
Requires-Dist: sphinx-contributors; extra == "doc"
Requires-Dist: scikit-learn; extra == "doc"
Provides-Extra: dandi
Requires-Dist: dandi; extra == "dandi"
Requires-Dist: fsspec; extra == "dandi"
Requires-Dist: requests; extra == "dandi"
Requires-Dist: aiohttp; extra == "dandi"
Dynamic: license-file
